odoo/addons/base_partner_merge_user_consolidation/README.rst
odoo/addons/base_partner_merge_user_consolidation/__init__.py
odoo/addons/base_partner_merge_user_consolidation/__manifest__.py
odoo/addons/base_partner_merge_user_consolidation/i18n/base_partner_merge_user_consolidation.pot
odoo/addons/base_partner_merge_user_consolidation/readme/CONTRIBUTORS.rst
odoo/addons/base_partner_merge_user_consolidation/readme/DESCRIPTION.rst
odoo/addons/base_partner_merge_user_consolidation/static/description/icon.png
odoo/addons/base_partner_merge_user_consolidation/static/description/index.html
odoo/addons/base_partner_merge_user_consolidation/tests/__init__.py
odoo/addons/base_partner_merge_user_consolidation/tests/test_partner_merge_user_consolidation.py
odoo/addons/base_partner_merge_user_consolidation/wizard/__init__.py
odoo/addons/base_partner_merge_user_consolidation/wizard/base_partner_merge.py
odoo_addon_base_partner_merge_user_consolidation-16.0.1.0.0.1.dist-info/METADATA
odoo_addon_base_partner_merge_user_consolidation-16.0.1.0.0.1.dist-info/WHEEL
odoo_addon_base_partner_merge_user_consolidation-16.0.1.0.0.1.dist-info/top_level.txt
odoo_addon_base_partner_merge_user_consolidation-16.0.1.0.0.1.dist-info/RECORD
