Metadata-Version: 2.1
Name: odoo-addon-base_partner_merge_user_consolidation
Version: 16.0.1.0.0.1
Summary: After merging contacts, automatically consolidate their linked user accounts.
Home-page: https://github.com/OCA/partner-contact
Author: Odoo Community Association (OCA), Therp BV
Author-email: support@odoo-community.org
License: AGPL-3
Classifier: Programming Language :: Python
Classifier: Framework :: Odoo
Classifier: Framework :: Odoo :: 16.0
Classifier: License :: OSI Approved :: GNU Affero General Public License v3
Classifier: Development Status :: 4 - Beta
Requires-Python: >=3.10
Requires-Dist: odoo<16.1dev,>=16.0a
